vartests/__init__.py
vartests/vartests.py
vartests/version.py
vartests-0.2.4.dist-info/METADATA
vartests-0.2.4.dist-info/WHEEL
vartests-0.2.4.dist-info/RECORD
